PythonWebShenduXuexiShiyongZhinanChuyiFix1/README.md
PythonWebShenduXuexiShiyongZhinanChuyiFix1/__init__.py
PythonWebShenduXuexiShiyongZhinanChuyiFix1/__main__.py
PythonWebShenduXuexiShiyongZhinanChuyiFix1/file.epub
PythonWebShenduXuexiShiyongZhinanChuyiFix1/index.html
PythonWebShenduXuexiShiyongZhinanChuyiFix1/css/__init__.py
PythonWebShenduXuexiShiyongZhinanChuyiFix1/css/annotations.css
PythonWebShenduXuexiShiyongZhinanChuyiFix1/css/main.css
PythonWebShenduXuexiShiyongZhinanChuyiFix1/css/normalize.css
PythonWebShenduXuexiShiyongZhinanChuyiFix1/css/popup.css
PythonWebShenduXuexiShiyongZhinanChuyiFix1/font/__init__.py
PythonWebShenduXuexiShiyongZhinanChuyiFix1/font/fontello.eot
PythonWebShenduXuexiShiyongZhinanChuyiFix1/font/fontello.svg
PythonWebShenduXuexiShiyongZhinanChuyiFix1/font/fontello.ttf
PythonWebShenduXuexiShiyongZhinanChuyiFix1/font/fontello.woff
PythonWebShenduXuexiShiyongZhinanChuyiFix1/img/__init__.py
PythonWebShenduXuexiShiyongZhinanChuyiFix1/img/annotator-glyph-sprite.png
PythonWebShenduXuexiShiyongZhinanChuyiFix1/img/annotator-icon-sprite.png
PythonWebShenduXuexiShiyongZhinanChuyiFix1/img/apple-touch-icon.png
PythonWebShenduXuexiShiyongZhinanChuyiFix1/img/cancelfullscreen.png
PythonWebShenduXuexiShiyongZhinanChuyiFix1/img/close.png
PythonWebShenduXuexiShiyongZhinanChuyiFix1/img/fullscreen.png
PythonWebShenduXuexiShiyongZhinanChuyiFix1/img/loader.gif
PythonWebShenduXuexiShiyongZhinanChuyiFix1/img/menu-icon.png
PythonWebShenduXuexiShiyongZhinanChuyiFix1/img/save.png
PythonWebShenduXuexiShiyongZhinanChuyiFix1/img/saved.png
PythonWebShenduXuexiShiyongZhinanChuyiFix1/img/settings-s.png
PythonWebShenduXuexiShiyongZhinanChuyiFix1/img/settings.png
PythonWebShenduXuexiShiyongZhinanChuyiFix1/img/star.png
PythonWebShenduXuexiShiyongZhinanChuyiFix1/js/__init__.py
PythonWebShenduXuexiShiyongZhinanChuyiFix1/js/epub.js
PythonWebShenduXuexiShiyongZhinanChuyiFix1/js/epub.min.js
PythonWebShenduXuexiShiyongZhinanChuyiFix1/js/epub.min.map
python_web_shendu_xuexi_shiyong_zhinan_chuyi_fix1-2025.3.25.0.dist-info/METADATA
python_web_shendu_xuexi_shiyong_zhinan_chuyi_fix1-2025.3.25.0.dist-info/WHEEL
python_web_shendu_xuexi_shiyong_zhinan_chuyi_fix1-2025.3.25.0.dist-info/entry_points.txt
python_web_shendu_xuexi_shiyong_zhinan_chuyi_fix1-2025.3.25.0.dist-info/top_level.txt
python_web_shendu_xuexi_shiyong_zhinan_chuyi_fix1-2025.3.25.0.dist-info/RECORD
